AnonymixTicket/__init__.py
AnonymixTicket/gradio_app.py
AnonymixTicket/utils.py
AnonymixTicket/data/logo.png
tests/__init__.py
tests/test_utils.py
AnonymixTicket-0.1.dist-info/METADATA
AnonymixTicket-0.1.dist-info/WHEEL
AnonymixTicket-0.1.dist-info/entry_points.txt
AnonymixTicket-0.1.dist-info/top_level.txt
AnonymixTicket-0.1.dist-info/RECORD
